plotreset/__init__.py
plotreset/custom.py
plotreset/defaults.py
plotreset/styles.py
plotreset/templates.py
plotreset/utils.py
plotreset-0.5.3.dist-info/licenses/LICENSE
plotreset-0.5.3.dist-info/METADATA
plotreset-0.5.3.dist-info/WHEEL
plotreset-0.5.3.dist-info/top_level.txt
plotreset-0.5.3.dist-info/RECORD
