Metadata-Version: 2.4
Name: plotreset
Version: 0.5.3
Summary: A wrapper for matplotlib library to make academic plots with ease.
Author-email: Anoop K Chandran <anoopkcn@gmail.com>
License: MIT License
Project-URL: Homepage, https://github.com/anoopkcn/plotreset
Project-URL: Documentation, https://github.com/anoopkcn/plotreset
Project-URL: Repository, https://github.com/anoopkcn/plotreset.git
Project-URL: Issues, https://github.com/anoopkcn/plotreset/issues
Keywords: plot,academic,matplotlib,latex,plotreset,mpl,style,wrapper,plotting,plotting-library
Classifier: Development Status :: 5 - Production/Stable
Classifier: Intended Audience :: Science/Research
Classifier: Topic :: Scientific/Engineering
Classifier: Operating System :: Microsoft :: Windows
Classifier: Operating System :: Unix
Classifier: Operating System :: MacOS
Classifier: License :: OSI Approved :: MIT License
Classifier: Programming Language :: Python :: 3.10
Classifier: Programming Language :: Python :: 3.11
Classifier: Programming Language :: Python :: 3.12
Classifier: Programming Language :: Python :: 3.13
Requires-Python: >=3.10.0
License-File: LICENSE
Requires-Dist: cycler>=0.12.1
Requires-Dist: matplotlib>=3.9.2
Dynamic: license-file
